[
  {
    "category1": "IT・プログラミング・開発",
    "category2": "AI・機械学習",
    "category3": ""
  },
  {
    "category1": "IT・プログラミング・開発",
    "category2": "Mac・Windowsアプリ開発",
    "category3": ""
  },
  {
    "category1": "IT・プログラミング・開発",
    "category2": "QA・テスト・コードレビュー",
    "category3": ""
  },
  {
    "category1": "IT・プログラミング・開発",
    "category2": "Webアプリケーション開発",
    "category3": ""
  },
  {
    "category1": "IT・プログラミング・開発",
    "category2": "その他（IT・プログラミング・開発）",
    "category3": ""
  },
  {
    "category1": "IT・プログラミング・開発",
    "category2": "ゲーム開発・VR開発",
    "category3": ""
  },
  {
    "category1": "IT・プログラミング・開発",
    "category2": "サーバー・インフラ構築",
    "category3": ""
  },
  {
    "category1": "IT・プログラミング・開発",
    "category2": "システム開発",
    "category3": ""
  },
  {
    "category1": "IT・プログラミング・開発",
    "category2": "ハードウェア設計・開発・工作",
    "category3": ""
  },
  {
    "category1": "IT・プログラミング・開発",
    "category2": "プログラミングレッスン",
    "category3": ""
  },
  {
    "category1": "IT・プログラミング・開発",
    "category2": "プログラミング・ソフトウェア",
    "category3": ""
  },
  {
    "category1": "IT・プログラミング・開発",
    "category2": "モバイルアプリ開発",
    "category3": ""
  },
  {
    "category1": "IT・プログラミング・開発",
    "category2": "保守・運用・管理",
    "category3": ""
  }
]
